AUTHORS.md
CONTRIBUTING.md
HISTORY.md
LICENSE
MANIFEST.in
README.md
setup.cfg
setup.py
epipearl/__init__.py
epipearl/epipearl.py
epipearl/errors.py
epipearl.egg-info/PKG-INFO
epipearl.egg-info/SOURCES.txt
epipearl.egg-info/dependency_links.txt
epipearl.egg-info/not-zip-safe
epipearl.egg-info/requires.txt
epipearl.egg-info/top_level.txt
epipearl/endpoints/__init__.py
epipearl/endpoints/admin.py
epipearl/endpoints/webui_channel.py
epipearl/endpoints/webui_config.py
epipearl/endpoints/webui_mhpearl.py
tests/__init__.py
tests/check-tags.py
tests/conftest.py
tests/dev-epiphan006-all_logs.zip
tests/dev-epiphan006.configdb.txt
tests/get-params.sh
tests/layout-live.json
tests/layout-lowbr.json
tests/layout-pn.json
tests/layout-pr.json
tests/resp_delete_channel_missing_success_message.html
tests/resp_delete_channel_ok.html
tests/resp_delete_recorder_missing_success_message.html
tests/resp_delete_recorder_ok.html
tests/resp_get_infocfg_ok.html
tests/resp_set_channel_rtmp_ok.html
tests/resp_set_date_and_time_invalid_proto.html
tests/resp_set_date_and_time_invalid_tz.html
tests/resp_set_date_and_time_not_authorized.html
tests/resp_set_date_and_time_ok.html
tests/resp_set_date_and_time_proto_didnot_take.html
tests/resp_set_mhpearl_settings_ok.html
tests/resp_set_recorder_channels_ok.html
tests/resp_set_recorder_settings_ok.html
tests/resp_set_source_deinterlacing_ok.html
tests/resp_sysinfo.json
tests/sample.html
tests/set-params.sh
tests/talk-curl.sh
tests/test_config.py
tests/test_epipearl.py
tests/test_webui_channel_endpoints.py
tests/test_webui_config_endpoints.py
tests/test_webui_epipearl.py
tests/test_webui_mhpearl_endpoints.py
tests/touchscreen.html
tests/xuxu.html
tests/xuxuxuxuxux