Metadata-Version: 1.1
Name: epipearl
Version: 0.2.0
Summary: python client for epiphan-pearl http api
Home-page: https://github.com/harvard-dce/epipearl
Author: nmaekawa
Author-email: nmaekawa@g.harvard.edu
License: Apache 2.0
Keywords: epipearl
Platform: UNKNOWN
Classifier: Development Status :: 2 - Pre-Alpha
Classifier: Intended Audience :: Developers
Classifier: License :: OSI Approved :: Apache Software License
Classifier: Natural Language :: English
Classifier: Programming Language :: Python :: 2.6
Classifier: Programming Language :: Python :: 2.7
